MANIFEST.in
README.rst
TITLE.txt
lh-agpl3-LICENSE.txt
setup.py
bin/provisionBisos.sh
bisos2/__init__.py
bisos2.provision.egg-info/PKG-INFO
bisos2.provision.egg-info/SOURCES.txt
bisos2.provision.egg-info/dependency_links.txt
bisos2.provision.egg-info/namespace_packages.txt
bisos2.provision.egg-info/not-zip-safe
bisos2.provision.egg-info/requires.txt
bisos2.provision.egg-info/top_level.txt
bisos2/provision/__init__.py
bisos2/provision/provisionPkgThis.py